bw_essentials/__init__.py
bw_essentials/s3_utils/__init__.py
bw_essentials/s3_utils/s3_utils.py
bw_essentials-0.1.3.dist-info/METADATA
bw_essentials-0.1.3.dist-info/WHEEL
bw_essentials-0.1.3.dist-info/top_level.txt
bw_essentials-0.1.3.dist-info/RECORD
